oxen/__init__.py
oxen/clip_nlcd.py
test/__init__.py
test/test___init__.py
lcmap_oxen-0.1.1.dist-info/LICENSE
lcmap_oxen-0.1.1.dist-info/METADATA
lcmap_oxen-0.1.1.dist-info/WHEEL
lcmap_oxen-0.1.1.dist-info/entry_points.txt
lcmap_oxen-0.1.1.dist-info/top_level.txt
lcmap_oxen-0.1.1.dist-info/RECORD
