Metadata-Version: 2.1
Name: lcmap-oxen
Version: 0.1.1
Summary: Create LCMAP aux tiles
Home-page: http://eroslab.cr.usgs.gov/lcmap/oxen
Author: USGS EROS LCMAP
Author-email: 
License: Unlicense
Keywords: usgs lcmap eros
Platform: UNKNOWN
Classifier: Development Status :: 5 - Production/Stable
Classifier: License :: Public Domain
Classifier: Programming Language :: Python :: 3.8
Provides-Extra: dev
Requires-Dist: twine ; extra == 'dev'
Provides-Extra: doc
Requires-Dist: sphinx ; extra == 'doc'
Requires-Dist: sphinx-autobuild ; extra == 'doc'
Requires-Dist: sphinx-rtd-theme ; extra == 'doc'
Provides-Extra: test
Requires-Dist: pytest ; extra == 'test'
Requires-Dist: pytest-cov ; extra == 'test'
